lazycms/__init__.py
lazycms/config.py
lazycms/entity.py
lazycms/lazycms.py
lazycms/storage.py
lazycms/utils.py
lazycms-0.1.0.dist-info/LICENSE
lazycms-0.1.0.dist-info/METADATA
lazycms-0.1.0.dist-info/WHEEL
lazycms-0.1.0.dist-info/top_level.txt
lazycms-0.1.0.dist-info/RECORD
