Metadata-Version: 2.1
Name: lazycms
Version: 0.1.0
Summary: Minimalistic CMS in Python with Markdown content
Home-page: https://github.com/neurophant/lazycms/
Author: Anton Smolin
Author-email: smolin.anton@gmail.com
License: MIT
Keywords: markdown cms minimalistic
Classifier: Development Status :: 3 - Alpha
Classifier: Environment :: Console
Classifier: Framework :: FastAPI
Classifier: Intended Audience :: Developers
Classifier: Intended Audience :: Information Technology
Classifier: Intended Audience :: Other Audience
Classifier: License :: OSI Approved :: MIT License
Classifier: Programming Language :: Python :: 3.12
Classifier: Topic :: Internet :: WWW/HTTP :: Dynamic Content :: Content Management System
Classifier: Topic :: Software Development :: Libraries
Classifier: Topic :: Text Processing :: Markup :: Markdown
License-File: LICENSE
Requires-Dist: fastapi <1.0.0,>=0.111.0
Requires-Dist: Jinja2 <4.0.0,>=3.1.4
Requires-Dist: Markdown <4.0,>=3.6
Requires-Dist: PyYAML <7.0.0,>=6.0.1
Requires-Dist: python-slugify <9.0.0,>=8.0.4
Requires-Dist: pydantic <3.0.0,>=2.8.2
